Workbook

Sheet Tổng quan
A1: TASKGENIE API TEST REPORT Inventory, full API smoke test, page mapping và defect summary — 2026-07-20 | B1: TASKGENIE API TEST REPORT Inventory, full API smoke test, page mapping và defect summary — 2026-07-20 | C1: TASKGENIE API TEST REPORT Inventory, full API smoke test, page mapping và defect summary — 2026-07-20 | D1: TASKGENIE API TEST REPORT Inventory, full API smoke test, page mapping và defect summary — 2026-07-20 | E1: TASKGENIE API TEST REPORT Inventory, full API smoke test, page mapping và defect summary — 2026-07-20 | F1: TASKGENIE API TEST REPORT Inventory, full API smoke test, page mapping và defect summary — 2026-07-20 | G1: TASKGENIE API TEST REPORT Inventory, full API smoke test, page mapping và defect summary — 2026-07-20 | H1: TASKGENIE API TEST REPORT Inventory, full API smoke test, page mapping và defect summary — 2026-07-20
A2: TASKGENIE API TEST REPORT Inventory, full API smoke test, page mapping và defect summary — 2026-07-20 | B2: TASKGENIE API TEST REPORT Inventory, full API smoke test, page mapping và defect summary — 2026-07-20 | C2: TASKGENIE API TEST REPORT Inventory, full API smoke test, page mapping và defect summary — 2026-07-20 | D2: TASKGENIE API TEST REPORT Inventory, full API smoke test, page mapping và defect summary — 2026-07-20 | E2: TASKGENIE API TEST REPORT Inventory, full API smoke test, page mapping và defect summary — 2026-07-20 | F2: TASKGENIE API TEST REPORT Inventory, full API smoke test, page mapping và defect summary — 2026-07-20 | G2: TASKGENIE API TEST REPORT Inventory, full API smoke test, page mapping và defect summary — 2026-07-20 | H2: TASKGENIE API TEST REPORT Inventory, full API smoke test, page mapping và defect summary — 2026-07-20
A4: TỔNG API | B4: TỔNG API | C4: PASS | D4: PASS | E4: FAIL | F4: FAIL | G4: SUCCESS RATE | H4: SUCCESS RATE
A5: =COUNTA('API Catalog'!$A$4:$A$112) -> 109 | C5: =COUNTIF('API Catalog'!$O$4:$O$112,"PASS") -> 109 | E5: =COUNTA('API Catalog'!$A$4:$A$112)-COUNTIF('API Catalog'!$O$4:$O$112,"PASS") -> 0 | G5: =COUNTIF('API Catalog'!$O$4:$O$112,"PASS")/COUNTA('API Catalog'!$A$4:$A$112) -> 1
A8: QUALITY & AUTOMATION
A9: Automated tests | B9: 59 | C9: Passed | D9: 59 | E9: Failed | F9: 0 | G9: API smoke operations | H9: 109
A10: Swagger paths | B10: 93 | C10: Operations executed | D10: 109 | E10: Missing operations | F10: 0 | G10: JWT revoked-token check | H10: PASS
A11: Environment | B11: ASP.NET Development | C11: Database | D11: EF Core InMemory | E11: External AI | F11: Hugging Face real model | G11: Cloudinary | H11: Upload + cleanup verified
A13: METHOD | B13: SỐ API | C13: TỶ TRỌNG | E13: FINDING | F13: SEVERITY | G13: STATUS | H13: HÀNH ĐỘNG
A14: GET | B14: =COUNTIF('API Catalog'!$C$4:$C$112,A14) -> 53 | C14: =B14/COUNTA('API Catalog'!$A$4:$A$112) -> 0.48623853 | E14: Google invalid-token trả đúng HTTP 401 | F14: High | G14: Resolved | H14: Đã map UnauthorizedAccessException → 401
A15: POST | B15: =COUNTIF('API Catalog'!$C$4:$C$112,A15) -> 32 | C15: =B15/COUNTA('API Catalog'!$A$4:$A$112) -> 0.29357798 | E15: Microsoft.OpenApi đã nâng lên 2.7.5 | F15: High | G15: Resolved | H15: Quét package vulnerable: không còn advisory
A16: PUT | B16: =COUNTIF('API Catalog'!$C$4:$C$112,A16) -> 12 | C16: =B16/COUNTA('API Catalog'!$A$4:$A$112) -> 0.11009174 | E16: Logout revoke JWT; token cũ trả 401 | F16: High | G16: Verified | H16: Giữ regression test cho JTI revocation
A17: DELETE | B17: =COUNTIF('API Catalog'!$C$4:$C$112,A17) -> 12 | C17: =B17/COUNTA('API Catalog'!$A$4:$A$112) -> 0.11009174 | E17: Cloudinary secret từng nằm trong Git history | F17: High | G17: Open | H17: Rotate key và cân nhắc purge history trước production
A20: TEST SCOPE
A21: Nguồn inventory | B21: Swagger/OpenAPI runtime | C21: Operations | D21: 109 | E21: Test data | F21: Seed + resources tạm | G21: External mutation | H21: Cloudinary assets đã cleanup
A22: Phạm vi | B22: Tất cả 109 operations | C22: Unit/integration | D22: 59/59 pass | E22: AI | F22: Model thật, không fallback | G22: Database | H22: InMemory — không ảnh hưởng DB thật
A23: Kết luận | B23: 109/109 API đạt tiêu chí; 108 happy-path 2xx + 1 negative Google token đúng 401; revoked JWT đúng 401

Sheet API Catalog
A1: TASKGENIE API CATALOG Input, output, mục đích, vị trí frontend đề xuất và actual response đầy đủ cho 109 operations qua JWT | B1: TASKGENIE API CATALOG Input, output, mục đích, vị trí frontend đề xuất và actual response đầy đủ cho 109 operations qua JWT | C1: TASKGENIE API CATALOG Input, output, mục đích, vị trí frontend đề xuất và actual response đầy đủ cho 109 operations qua JWT | D1: TASKGENIE API CATALOG Input, output, mục đích, vị trí frontend đề xuất và actual response đầy đủ cho 109 operations qua JWT | E1: TASKGENIE API CATALOG Input, output, mục đích, vị trí frontend đề xuất và actual response đầy đủ cho 109 operations qua JWT | F1: TASKGENIE API CATALOG Input, output, mục đích, vị trí frontend đề xuất và actual response đầy đủ cho 109 operations qua JWT | G1: TASKGENIE API CATALOG Input, output, mục đích, vị trí frontend đề xuất và actual response đầy đủ cho 109 operations qua JWT | H1: TASKGENIE API CATALOG Input, output, mục đích, vị trí frontend đề xuất và actual response đầy đủ cho 109 operations qua JWT | I1: TASKGENIE API CATALOG Input, output, mục đích, vị trí frontend đề xuất và actual response đầy đủ cho 109 operations qua JWT | J1: TASKGENIE API CATALOG Input, output, mục đích, vị trí frontend đề xuất và actual response đầy đủ cho 109 operations qua JWT | K1: TASKGENIE API CATALOG Input, output, mục đích, vị trí frontend đề xuất và actual response đầy đủ cho 109 operations qua JWT | L1: TASKGENIE API CATALOG Input, output, mục đích, vị trí frontend đề xuất và actual response đầy đủ cho 109 operations qua JWT | M1: TASKGENIE API CATALOG Input, output, mục đích, vị trí frontend đề xuất và actual response đầy đủ cho 109 operations qua JWT | N1: TASKGENIE API CATALOG Input, output, mục đích, vị trí frontend đề xuất và actual response đầy đủ cho 109 operations qua JWT | O1: TASKGENIE API CATALOG Input, output, mục đích, vị trí frontend đề xuất và actual response đầy đủ cho 109 operations qua JWT | P1: TASKGENIE API CATALOG Input, output, mục đích, vị trí frontend đề xuất và actual response đầy đủ cho 109 operations qua JWT | Q1: TASKGENIE API CATALOG Input, output, mục đích, vị trí frontend đề xuất và actual response đầy đủ cho 109 operations qua JWT
A2: TASKGENIE API CATALOG Input, output, mục đích, vị trí frontend đề xuất và actual response đầy đủ cho 109 operations qua JWT | B2: TASKGENIE API CATALOG Input, output, mục đích, vị trí frontend đề xuất và actual response đầy đủ cho 109 operations qua JWT | C2: TASKGENIE API CATALOG Input, output, mục đích, vị trí frontend đề xuất và actual response đầy đủ cho 109 operations qua JWT | D2: TASKGENIE API CATALOG Input, output, mục đích, vị trí frontend đề xuất và actual response đầy đủ cho 109 operations qua JWT | E2: TASKGENIE API CATALOG Input, output, mục đích, vị trí frontend đề xuất và actual response đầy đủ cho 109 operations qua JWT | F2: TASKGENIE API CATALOG Input, output, mục đích, vị trí frontend đề xuất và actual response đầy đủ cho 109 operations qua JWT | G2: TASKGENIE API CATALOG Input, output, mục đích, vị trí frontend đề xuất và actual response đầy đủ cho 109 operations qua JWT | H2: TASKGENIE API CATALOG Input, output, mục đích, vị trí frontend đề xuất và actual response đầy đủ cho 109 operations qua JWT | I2: TASKGENIE API CATALOG Input, output, mục đích, vị trí frontend đề xuất và actual response đầy đủ cho 109 operations qua JWT | J2: TASKGENIE API CATALOG Input, output, mục đích, vị trí frontend đề xuất và actual response đầy đủ cho 109 operations qua JWT | K2: TASKGENIE API CATALOG Input, output, mục đích, vị trí frontend đề xuất và actual response đầy đủ cho 109 operations qua JWT | L2: TASKGENIE API CATALOG Input, output, mục đích, vị trí frontend đề xuất và actual response đầy đủ cho 109 operations qua JWT | M2: TASKGENIE API CATALOG Input, output, mục đích, vị trí frontend đề xuất và actual response đầy đủ cho 109 operations qua JWT | N2: TASKGENIE API CATALOG Input, output, mục đích, vị trí frontend đề xuất và actual response đầy đủ cho 109 operations qua JWT | O2: TASKGENIE API CATALOG Input, output, mục đích, vị trí frontend đề xuất và actual response đầy đủ cho 109 operations qua JWT | P2: TASKGENIE API CATALOG Input, output, mục đích, vị trí frontend đề xuất và actual response đầy đủ cho 109 operations qua JWT | Q2: TASKGENIE API CATALOG Input, output, mục đích, vị trí frontend đề xuất và actual response đầy đủ cho 109 operations qua JWT
A3: STT | B3: Controller | C3: Method | D3: Endpoint | E3: Dùng để làm gì | F3: Nên ở trang nào | G3: Header / Auth | H3: Path Input | I3: Query Input | J3: Body Schema | K3: Input Example | L3: Expected Output | M3: Actual HTTP | N3: Actual Output | O3: Test Result | P3: Duration (ms) | Q3: Notes
A4: 1 | B4: ActivityLogs | C4: GET | D4: /api/ActivityLogs | E4: Lấy toàn bộ nhật ký hoạt động, có thể lọc theo query. | F4: Reports Dashboard / Activity Log / Audit Trail | G4: Authorization: Bearer <JWT>; Content-Type theo body | H4: Không có | I4: limit: integer(int32) | J4: Không có body | K4: Query: {"limit":1} | L4: 200 JSON object/array theo nghiệp vụ. | M4: 200 | N4: [{"logId":1,"userId":1,"userName":"Nguyen Van An","action":"TASK_CREATED","entityType":"TASK","entityId":14,"createdAt":"2026-07-20T06:59:29.834847Z"}] | O4: PASS | P4: 59 | Q4: Smoke test dùng Bearer JWT trên database InMemory; không ảnh hưởng dữ liệu thật.
A5: 2 | B5: ActivityLogs | C5: GET | D5: /api/ActivityLogs/entity/{entityType}/{entityId} | E5: Truy vết lịch sử thay đổi của một thực thể. | F5: Reports Dashboard / Activity Log / Audit Trail | G5: Authorization: Bearer <JWT>; Content-Type theo body | H5: entityType: string (required); entityId: integer(int32) (required) | I5: Không có | J5: Không có body | K5: Path: {"entityType":"Task","entityId":8} | L5: 200 JSON object/array theo nghiệp vụ. | M5: 200 | N5: [] | O5: PASS | P5: 23 | Q5: Smoke test dùng Bearer JWT trên database InMemory; không ảnh hưởng dữ liệu thật.
A6: 3 | B6: ActivityLogs | C6: GET | D6: /api/ActivityLogs/project/{projectId} | E6: Lấy audit trail của một dự án. | F6: Reports Dashboard / Activity Log / Audit Trail | G6: Authorization: Bearer <JWT>; Content-Type theo body | H6: projectId: integer(int32) (required) | I6: limit: integer(int32) | J6: Không có body | K6: Path: {"projectId":3} Query: {"limit":1} | L6: 200 JSON object/array theo nghiệp vụ. | M6: 200 | N6: [] | O6: PASS | P6: 43 | Q6: Smoke test dùng Bearer JWT trên database InMemory; không ảnh hưởng dữ liệu thật.
A7: 4 | B7: ActivityLogs | C7: GET | D7: /api/ActivityLogs/user/{userId} | E7: Lấy nhật ký hoạt động của một người dùng. | F7: Reports Dashboard / Activity Log / Audit Trail | G7: Authorization: Bearer <JWT>; Content-Type theo body | H7: userId: integer(int32) (required) | I7: Không có | J7: Không có body | K7: Path: {"userId":1} | L7: 200 JSON object/array theo nghiệp vụ. | M7: 200 | N7: [{"logId":1,"userId":1,"userName":"Nguyen Van An","action":"TASK_CREATED","entityType":"TASK","entityId":14,"createdAt":"2026-07-20T06:59:29.834847Z"}] | O7: PASS | P7: 22 | Q7: Smoke test dùng Bearer JWT trên database InMemory; không ảnh hưởng dữ liệu thật.
A8: 5 | B8: Admin | C8: GET | D8: /api/Admin/platform-stats | E8: Lấy thống kê tổng quan nền tảng cho quản trị viên. | F8: Administration Center / Platform Overview | G8: Authorization: Bearer <JWT>; Content-Type theo body | H8: Không có | I8: Không có | J8: Không có body | K8: Không có path/query/body; dùng Bearer JWT trừ endpoint AllowAnonymous. | L8: 200 JSON object/array theo nghiệp vụ. | M8: 200 | N8: {"users":6,"organizations":1,"projects":3,"tasks":14,"tasksDone":5} | O8: PASS | P8: 77 | Q8: Smoke test dùng Bearer JWT trên database InMemory; không ảnh hưởng dữ liệu thật.
A9: 6 | B9: AiAnalysis | C9: GET | D9: /api/ai-analysis/{taskId} | E9: Lấy kết quả phân tích AI gần nhất của task. | F9: Core AI Demo Panel / Task Detail / Project Dashboard | G9: Authorization: Bearer <JWT>; Content-Type theo body | H9: taskId: integer(int32) (required) | I9: Không có | J9: Không có body | K9: Path: {"taskId":8} | L9: 200 JSON object/array theo nghiệp vụ. | M9: 200 | N9: [] | O9: PASS | P9: 22 | Q9: Đã gọi Hugging Face model thật trong môi trường InMemory.
A10: 7 | B10: AiAnalysis | C10: POST | D10: /api/ai-analysis/{taskId}/classify | E10: Phân loại nội dung task bằng mô hình zero-shot. | F10: Task Detail → AI Analysis | G10: Authorization: Bearer <JWT>; Content-Type theo body | H10: taskId: integer(int32) (required) | I10: Không có | J10: Không có body | K10: Path: {"taskId":8} | L10: 200 JSON kết quả nghiệp vụ. | M10: 200 | N10: {"message":"Task classification and analysis completed successfully."} | O10: PASS | P10: 1147 | Q10: Đã gọi Hugging Face model thật trong môi trường InMemory.
A11: 8 | B11: AiAnalysis | C11: GET | D11: /api/ai-analysis/{taskId}/executions | E11: Lấy AI execution logs phục vụ audit và đánh giá model. | F11: Task Detail → AI History / Audit | G11: Authorization: Bearer <JWT>; Content-Type theo body | H11: taskId: integer(int32) (required) | I11: Không có | J11: Không có body | K11: Path: {"taskId":8} | L11: 200 JSON object/array theo nghiệp vụ. | M11: 200 | N11: [{"runId":"a6d8e507-6a6d-4efa-b750-4eb22937214b","taskId":8,"feature":"ASSIGNMENT_RECOMMENDATION","provider":"RULE_ENGINE+HUGGINGFACE","modelVersion":"assignment-v1","status":"SUCCEEDED","latencyMs":914,"errorMessage":null,"createdAt":"2026-07-20T06:59:31.806337Z"}] | O11: PASS | P11: 30 | Q11: Đã gọi Hugging Face model thật trong môi trường InMemory.
A12: 9 | B12: AiAnalysis | C12: POST | D12: /api/ai-analysis/{taskId}/risk | E12: Tính risk score, risk factors và giải thích AI cho task. | F12: Task Detail → AI Analysis | G12: Authorization: Bearer <JWT>; Content-Type theo body | H12: taskId: integer(int32) (required) | I12: Không có | J12: Không có body | K12: Path: {"taskId":8} | L12: 200 JSON kết quả nghiệp vụ. | M12: 200 | N12: {"runId":"fb86b7a8-dcc8-450d-a89d-2b251020fb55","taskId":8,"projectId":1,"totalScore":26.3,"riskLevel":"LOW","ruleVersion":"risk-v1","calculationMode":"RULES_WITH_AI_EXPLANATION","explanation":"Risk LOW (26,30/100). Main contributors: PROGRESS 58, DEADLINE 25, HISTORICAL 25. AI explanation: The Testing & QA task has a LOW risk score of 26.3. It is primarily driven by a tight deadline (25) and moderate progress (58), with minimal workload (12) and no dependencies (0). Historical data shows similar past performance (25). While the deadline adds pressure, overall risk remains low due to stable progress, manageable workload, and no critical dependencies.","mitigationActions":["Continue monitoring at the next progress update."],"factors":[{"code":"DEADLINE","rawValue":"daysRemaining=8;remainingHours=0;availableHours=64","score":25,"weight":0.3,"contribution":7.5,"evidence":"Deadline proximity and remaining-effort pressure."},{"code":"PROGRESS","rawValue":"progress=0;expected=0,0;staleDays=14","score":58,"weight":0.25,"contribution":14.5,"evidence":"Progress shortfall against elapsed schedule and update staleness."},{"code":"DEPENDENCY","rawValue":"incomplete=0;total=0;reportedBlocker=False","score":0,"weight":0.2,"contribution":0,"evidence":"Incomplete task dependencies."},{"code":"WORKLOAD","rawValue":"activeTasks=1,0;availableHours=0,0;remainingHours=0","score":12,"weight":0.15,"contribution":1.8,"evidence":"Assignee workload and declared availability."},{"code":"HISTORICAL","rawValue":"deadlineScore=missing","score":25,"weight":0.1,"contribution":2.5,"evidence":"No historical evaluation; uncertainty baseline applied."}],"createdAt":"2026-07-20T06:59:40.554156Z"} | O12: PASS | P12: 1259 | Q12: Đã gọi Hugging Face model thật trong môi trường InMemory.
A13: 10 | B13: AiAnalysis | C13: GET | D13: /api/ai-analysis/{taskId}/risk-history | E13: Lấy lịch sử risk score và risk factors của task. | F13: Task Detail → AI History / Audit | G13: Authorization: Bearer <JWT>; Content-Type theo body | H13: taskId: integer(int32) (required) | I13: Không có | J13: Không có body | K13: Path: {"taskId":8} | L13: 200 JSON object/array theo nghiệp vụ. | M13: 200 | N13: [] | O13: PASS | P13: 34 | Q13: Đã gọi Hugging Face model thật trong môi trường InMemory.
A14: 11 | B14: AiAnalysis | C14: POST | D14: /api/ai-analysis/{taskId}/summary | E14: Sinh bản tóm tắt task bằng mô hình AI. | F14: Task Detail → AI Analysis | G14: Authorization: Bearer <JWT>; Content-Type theo body | H14: taskId: integer(int32) (required) | I14: Không có | J14: Không có body | K14: Path: {"taskId":8} | L14: 200 JSON kết quả nghiệp vụ. | M14: 200 | N14: {"message":"Task summary generated successfully."} | O14: PASS | P14: 25 | Q14: Đã gọi Hugging Face model thật trong môi trường InMemory.
A15: 12 | B15: AiAnalysis | C15: POST | D15: /api/ai-analysis/project/{projectId}/analyze-all | E15: Phân tích rủi ro hàng loạt cho toàn bộ task trong dự án. | F15: Project Dashboard → AI Risk | G15: Authorization: Bearer <JWT>; Content-Type theo body | H15: projectId: integer(int32) (required) | I15: Không có | J15: Không có body | K15: Path: {"projectId":1} | L15: 200 JSON kết quả nghiệp vụ. | M15: 200 | N15: {"totalActive":5,"criticalRisk":0,"highRisk":0,"mediumRisk":4,"lowRisk":1,"averageScore":45.82,"status":"WARNING","warnings":[]} | O15: PASS | P15: 7949 | Q15: Đã gọi Hugging Face model thật trong môi trường InMemory.
... A112: 109 | B112: UserScores | C112: GET | D112: /api/user-scores/user/{userId}/summary | E112: Lấy tổng hợp điểm và hiệu suất người dùng. | F112: Evaluation Center / Leaderboard / Reports | G112: Authorization: Bearer <JWT>; Content-Type theo body | H112: userId: integer(int32) (required) | I112: Không có | J112: Không có body | K112: Path: {"userId":1} | L112: 200 JSON object/array theo nghiệp vụ. | M112: 200 | N112: {"userId":1,"userName":"Nguyen Van An","avatar":null,"totalScore":126,"totalRewardPoints":126,"totalPenaltyPoints":0,"level":"Silver","levelMinScore":100,"levelMaxScore":299,"progressToNextLevel":13} | O112: PASS | P112: 19 | Q112: Smoke test dùng Bearer JWT trên database InMemory; không ảnh hưởng dữ liệu thật.

Sheet Test Results
A1: API TEST RESULTS Actual HTTP evidence cho từng operation; full smoke trên InMemory + external provider checks | B1: API TEST RESULTS Actual HTTP evidence cho từng operation; full smoke trên InMemory + external provider checks | C1: API TEST RESULTS Actual HTTP evidence cho từng operation; full smoke trên InMemory + external provider checks | D1: API TEST RESULTS Actual HTTP evidence cho từng operation; full smoke trên InMemory + external provider checks | E1: API TEST RESULTS Actual HTTP evidence cho từng operation; full smoke trên InMemory + external provider checks | F1: API TEST RESULTS Actual HTTP evidence cho từng operation; full smoke trên InMemory + external provider checks | G1: API TEST RESULTS Actual HTTP evidence cho từng operation; full smoke trên InMemory + external provider checks | H1: API TEST RESULTS Actual HTTP evidence cho từng operation; full smoke trên InMemory + external provider checks | I1: API TEST RESULTS Actual HTTP evidence cho từng operation; full smoke trên InMemory + external provider checks
A2: API TEST RESULTS Actual HTTP evidence cho từng operation; full smoke trên InMemory + external provider checks | B2: API TEST RESULTS Actual HTTP evidence cho từng operation; full smoke trên InMemory + external provider checks | C2: API TEST RESULTS Actual HTTP evidence cho từng operation; full smoke trên InMemory + external provider checks | D2: API TEST RESULTS Actual HTTP evidence cho từng operation; full smoke trên InMemory + external provider checks | E2: API TEST RESULTS Actual HTTP evidence cho từng operation; full smoke trên InMemory + external provider checks | F2: API TEST RESULTS Actual HTTP evidence cho từng operation; full smoke trên InMemory + external provider checks | G2: API TEST RESULTS Actual HTTP evidence cho từng operation; full smoke trên InMemory + external provider checks | H2: API TEST RESULTS Actual HTTP evidence cho từng operation; full smoke trên InMemory + external provider checks | I2: API TEST RESULTS Actual HTTP evidence cho từng operation; full smoke trên InMemory + external provider checks
A3: TC ID | B3: Method | C3: Endpoint | D3: Scenario | E3: Expected | F3: Actual | G3: Result | H3: Evidence / Output | I3: Defect
A4: TC-API-001 | B4: GET | C4: /api/ActivityLogs | D4: Happy-path với Bearer JWT, seed data và resource tạm trên EF Core InMemory | E4: 200 JSON object/array theo nghiệp vụ. | F4: 200 | G4: PASS | H4: [{"logId":1,"userId":1,"userName":"Nguyen Van An","action":"TASK_CREATED","entityType":"TASK","entityId":14,"createdAt":"2026-07-20T06:59:29.834847Z"}]
A5: TC-API-002 | B5: GET | C5: /api/ActivityLogs/entity/{entityType}/{entityId} | D5: Happy-path với Bearer JWT, seed data và resource tạm trên EF Core InMemory | E5: 200 JSON object/array theo nghiệp vụ. | F5: 200 | G5: PASS | H5: []
A6: TC-API-003 | B6: GET | C6: /api/ActivityLogs/project/{projectId} | D6: Happy-path với Bearer JWT, seed data và resource tạm trên EF Core InMemory | E6: 200 JSON object/array theo nghiệp vụ. | F6: 200 | G6: PASS | H6: []
A7: TC-API-004 | B7: GET | C7: /api/ActivityLogs/user/{userId} | D7: Happy-path với Bearer JWT, seed data và resource tạm trên EF Core InMemory | E7: 200 JSON object/array theo nghiệp vụ. | F7: 200 | G7: PASS | H7: [{"logId":1,"userId":1,"userName":"Nguyen Van An","action":"TASK_CREATED","entityType":"TASK","entityId":14,"createdAt":"2026-07-20T06:59:29.834847Z"}]
A8: TC-API-005 | B8: GET | C8: /api/Admin/platform-stats | D8: Happy-path với Bearer JWT, seed data và resource tạm trên EF Core InMemory | E8: 200 JSON object/array theo nghiệp vụ. | F8: 200 | G8: PASS | H8: {"users":6,"organizations":1,"projects":3,"tasks":14,"tasksDone":5}
A9: TC-API-006 | B9: GET | C9: /api/ai-analysis/{taskId} | D9: Happy-path với Bearer JWT, seed data và resource tạm trên EF Core InMemory | E9: 200 JSON object/array theo nghiệp vụ. | F9: 200 | G9: PASS | H9: []
A10: TC-API-007 | B10: POST | C10: /api/ai-analysis/{taskId}/classify | D10: Happy-path với Bearer JWT, seed data và resource tạm trên EF Core InMemory | E10: 200 JSON kết quả nghiệp vụ. | F10: 200 | G10: PASS | H10: {"message":"Task classification and analysis completed successfully."}
A11: TC-API-008 | B11: GET | C11: /api/ai-analysis/{taskId}/executions | D11: Happy-path với Bearer JWT, seed data và resource tạm trên EF Core InMemory | E11: 200 JSON object/array theo nghiệp vụ. | F11: 200 | G11: PASS | H11: [{"runId":"a6d8e507-6a6d-4efa-b750-4eb22937214b","taskId":8,"feature":"ASSIGNMENT_RECOMMENDATION","provider":"RULE_ENGINE+HUGGINGFACE","modelVersion":"assignment-v1","status":"SUCCEEDED","latencyMs":914,"errorMessage":null,"createdAt":"2026-07-20T06:59:31.806337Z"}]
A12: TC-API-009 | B12: POST | C12: /api/ai-analysis/{taskId}/risk | D12: Happy-path với Bearer JWT, seed data và resource tạm trên EF Core InMemory | E12: 200 JSON kết quả nghiệp vụ. | F12: 200 | G12: PASS | H12: {"runId":"fb86b7a8-dcc8-450d-a89d-2b251020fb55","taskId":8,"projectId":1,"totalScore":26.3,"riskLevel":"LOW","ruleVersion":"risk-v1","calculationMode":"RULES_WITH_AI_EXPLANATION","explanation":"Risk LOW (26,30/100). Main contributors: PROGRESS 58, DEADLINE 25, HISTORICAL 25. AI explanation: The Testing & QA task has a LOW risk score of 26.3. It is primarily driven by a tight deadline (25) and moderate progress (58), with minimal workload (12) and no dependencies (0). Historical data shows similar past performance (25). While the deadline adds pressure, overall risk remains low due to stable progress, manageable workload, and no critical dependencies.","mitigationActions":["Continue monitoring at the next progress update."],"factors":[{"code":"DEADLINE","rawValue":"daysRemaining=8;remainingHours=0;availableHours=64","score":25,"weight":0.3,"contribution":7.5,"evidence":"Deadline proximity and remaining-effort pressure."},{"code":"PROGRESS","rawValue":"progress=0;expected=0,0;staleDays=14","score":58,"weight":0.25,"contribution":14.5,"evidence":"Progress shortfall against elapsed schedule and update staleness."},{"code":"DEPENDENCY","rawValue":"incomplete=0;total=0;reportedBlocker=False","score":0,"weight":0.2,"contribution":0,"evidence":"Incomplete task dependencies."},{"code":"WORKLOAD","rawValue":"activeTasks=1,0;availableHours=0,0;remainingHours=0","score":12,"weight":0.15,"contribution":1.8,"evidence":"Assignee workload and declared availability."},{"code":"HISTORICAL","rawValue":"deadlineScore=missing","score":25,"weight":0.1,"contribution":2.5,"evidence":"No historical evaluation; uncertainty baseline applied."}],"createdAt":"2026-07-20T06:59:40.554156Z"}
A13: TC-API-010 | B13: GET | C13: /api/ai-analysis/{taskId}/risk-history | D13: Happy-path với Bearer JWT, seed data và resource tạm trên EF Core InMemory | E13: 200 JSON object/array theo nghiệp vụ. | F13: 200 | G13: PASS | H13: []
A14: TC-API-011 | B14: POST | C14: /api/ai-analysis/{taskId}/summary | D14: Happy-path với Bearer JWT, seed data và resource tạm trên EF Core InMemory | E14: 200 JSON kết quả nghiệp vụ. | F14: 200 | G14: PASS | H14: {"message":"Task summary generated successfully."}
A15: TC-API-012 | B15: POST | C15: /api/ai-analysis/project/{projectId}/analyze-all | D15: Happy-path với Bearer JWT, seed data và resource tạm trên EF Core InMemory | E15: 200 JSON kết quả nghiệp vụ. | F15: 200 | G15: PASS | H15: {"totalActive":5,"criticalRisk":0,"highRisk":0,"mediumRisk":4,"lowRisk":1,"averageScore":45.82,"status":"WARNING","warnings":[]}
... A112: TC-API-109 | B112: GET | C112: /api/user-scores/user/{userId}/summary | D112: Happy-path với Bearer JWT, seed data và resource tạm trên EF Core InMemory | E112: 200 JSON object/array theo nghiệp vụ. | F112: 200 | G112: PASS | H112: {"userId":1,"userName":"Nguyen Van An","avatar":null,"totalScore":126,"totalRewardPoints":126,"totalPenaltyPoints":0,"level":"Silver","levelMinScore":100,"levelMaxScore":299,"progressToNextLevel":13}

Sheet Defect Log
A1: DEFECT & QUALITY LOG Các vấn đề xác nhận trong quá trình full API test và build/test suite | B1: DEFECT & QUALITY LOG Các vấn đề xác nhận trong quá trình full API test và build/test suite | C1: DEFECT & QUALITY LOG Các vấn đề xác nhận trong quá trình full API test và build/test suite | D1: DEFECT & QUALITY LOG Các vấn đề xác nhận trong quá trình full API test và build/test suite | E1: DEFECT & QUALITY LOG Các vấn đề xác nhận trong quá trình full API test và build/test suite | F1: DEFECT & QUALITY LOG Các vấn đề xác nhận trong quá trình full API test và build/test suite | G1: DEFECT & QUALITY LOG Các vấn đề xác nhận trong quá trình full API test và build/test suite | H1: DEFECT & QUALITY LOG Các vấn đề xác nhận trong quá trình full API test và build/test suite | I1: DEFECT & QUALITY LOG Các vấn đề xác nhận trong quá trình full API test và build/test suite | J1: DEFECT & QUALITY LOG Các vấn đề xác nhận trong quá trình full API test và build/test suite
A2: DEFECT & QUALITY LOG Các vấn đề xác nhận trong quá trình full API test và build/test suite | B2: DEFECT & QUALITY LOG Các vấn đề xác nhận trong quá trình full API test và build/test suite | C2: DEFECT & QUALITY LOG Các vấn đề xác nhận trong quá trình full API test và build/test suite | D2: DEFECT & QUALITY LOG Các vấn đề xác nhận trong quá trình full API test và build/test suite | E2: DEFECT & QUALITY LOG Các vấn đề xác nhận trong quá trình full API test và build/test suite | F2: DEFECT & QUALITY LOG Các vấn đề xác nhận trong quá trình full API test và build/test suite | G2: DEFECT & QUALITY LOG Các vấn đề xác nhận trong quá trình full API test và build/test suite | H2: DEFECT & QUALITY LOG Các vấn đề xác nhận trong quá trình full API test và build/test suite | I2: DEFECT & QUALITY LOG Các vấn đề xác nhận trong quá trình full API test và build/test suite | J2: DEFECT & QUALITY LOG Các vấn đề xác nhận trong quá trình full API test và build/test suite
A3: Defect ID | B3: Category | C3: Severity | D3: Priority | E3: Endpoint / Area | F3: Actual Result | G3: Expected Result | H3: Root Cause / Evidence | I3: Recommended Fix | J3: Status
A4: DEF-API-001 | B4: API Error Handling | C4: High | D4: P1 | E4: POST /api/auth/google | F4: Invalid token trả HTTP 401 và JSON lỗi an toàn | G4: HTTP 401; không trả 500 | H4: UnauthorizedAccessException đã được middleware map | I4: Giữ negative regression test | J4: Resolved
A5: DEF-SEC-001 | B5: Dependency Security | C5: High | D5: P1 | E5: Microsoft.OpenApi | F5: Đã nâng 2.4.1 → 2.7.5; vulnerability scan không còn advisory | G5: Không có high-severity advisory | H5: Package dễ tổn thương đã được thay thế | I5: Duy trì dependency scan trong CI | J5: Resolved
A6: OBS-AUTH-001 | B6: JWT Revocation | C6: High | D6: P1 | E6: POST /api/auth/logout | F6: Logout 200; token cũ gọi GET /api/Teams/my trả 401 | G6: Token đã logout phải bị từ chối | H6: InMemoryTokenRevocationService kiểm tra JTI | I6: Bổ sung integration regression test lâu dài | J6: Verified
A7: OBS-QLT-001 | B7: Test Coverage | C7: Medium | D7: P2 | E7: Whole solution | F7: 59/59 automated tests pass; coverage không được tính lại trong lượt smoke này | G7: Coverage theo critical use cases | H7: Full API smoke không thay thế line/branch coverage | I7: Chạy collect coverage trong CI và đặt threshold | J7: Open
A8: DEF-SEC-002 | B8: Secret Management | C8: High | D8: P1 | E8: Cloudinary credential | F8: Secret cũ từng nằm trong Git history | G8: Secret chỉ nằm trong User Secrets/env và đã rotate | H8: Credential từng được commit | I8: Rotate key; cân nhắc purge Git history trước production | J8: Open
A9: OBS-BLD-001 | B9: Nullable Analysis | C9: Low | D9: P3 | E9: OrganizationRepository.cs:43 | F9: Clean infrastructure build cảnh báo CS8602 | G9: Build không có nullable warning | H9: Có thể dereference giá trị null | I9: Thêm null guard hoặc điều chỉnh query projection | J9: Open

Sheet Page Mapping
A1: FRONTEND PAGE MAPPING Đề xuất vị trí tích hợp API theo module và giao diện hiện có | B1: FRONTEND PAGE MAPPING Đề xuất vị trí tích hợp API theo module và giao diện hiện có | C1: FRONTEND PAGE MAPPING Đề xuất vị trí tích hợp API theo module và giao diện hiện có | D1: FRONTEND PAGE MAPPING Đề xuất vị trí tích hợp API theo module và giao diện hiện có | E1: FRONTEND PAGE MAPPING Đề xuất vị trí tích hợp API theo module và giao diện hiện có
A2: FRONTEND PAGE MAPPING Đề xuất vị trí tích hợp API theo module và giao diện hiện có | B2: FRONTEND PAGE MAPPING Đề xuất vị trí tích hợp API theo module và giao diện hiện có | C2: FRONTEND PAGE MAPPING Đề xuất vị trí tích hợp API theo module và giao diện hiện có | D2: FRONTEND PAGE MAPPING Đề xuất vị trí tích hợp API theo module và giao diện hiện có | E2: FRONTEND PAGE MAPPING Đề xuất vị trí tích hợp API theo module và giao diện hiện có
A3: Controller | B3: Trang chính | C3: Trang phụ / Component | D3: Số API | E3: Mục đích UI
A4: ActivityLogs | B4: Reports Dashboard | C4: Activity Log / Audit Trail | D4: =COUNTIF('API Catalog'!$B$4:$B$112,A4) -> 4 | E4: Theo dõi lịch sử thao tác và truy vết thay đổi.
A5: Admin | B5: Administration Center | C5: Platform Overview | D5: =COUNTIF('API Catalog'!$B$4:$B$112,A5) -> 1 | E5: Chỉ dành cho quản trị hệ thống.
A6: AiAnalysis | B6: Core AI Demo Panel | C6: Task Detail / Project Dashboard | D6: =COUNTIF('API Catalog'!$B$4:$B$112,A6) -> 8 | E6: Hiển thị risk score, giải thích, workload và lịch sử AI.
A7: Auth | B7: Login / Register | C7: Authentication Module | D7: =COUNTIF('API Catalog'!$B$4:$B$112,A7) -> 4 | E7: Đăng ký, đăng nhập, Google OAuth, JWT và logout/revocation.
A8: Evaluations | B8: Evaluation Center | C8: User Performance Detail | D8: =COUNTIF('API Catalog'!$B$4:$B$112,A8) -> 5 | E8: Đánh giá thành viên và năng lực làm việc.
A9: Export | B9: Reports Dashboard | C9: Project Detail | D9: =COUNTIF('API Catalog'!$B$4:$B$112,A9) -> 2 | E9: Nút xuất báo cáo PDF/XLSX.
A10: Invitations | B10: Team Management | C10: Invitations Inbox | D10: =COUNTIF('API Catalog'!$B$4:$B$112,A10) -> 6 | E10: Mời và xử lý lời mời vào nhóm.
A11: Meetings | B11: Project Detail | C11: Meetings / Calendar | D11: =COUNTIF('API Catalog'!$B$4:$B$112,A11) -> 10 | E11: Quản lý cuộc họp và người tham dự.
A12: Notifications | B12: Header Notification Center | C12: Notifications Page | D12: =COUNTIF('API Catalog'!$B$4:$B$112,A12) -> 5 | E12: Thông báo, số chưa đọc và thao tác đã đọc.
A13: Organizations | B13: Administration Center | C13: Organization Detail | D13: =COUNTIF('API Catalog'!$B$4:$B$112,A13) -> 7 | E13: Quản lý tổ chức, dự án và đánh giá dự án.
A14: Projects | B14: Project Management | C14: Dashboard / Project Detail | D14: =COUNTIF('API Catalog'!$B$4:$B$112,A14) -> 8 | E14: CRUD dự án, thành viên, tổng kết và đóng dự án.
A15: Skills | B15: User Profile | C15: Team Management / Skill Matrix | D15: =COUNTIF('API Catalog'!$B$4:$B$112,A15) -> 7 | E15: Danh mục kỹ năng và kỹ năng người dùng.
... A24: Users | B24: User Profile | C24: Team Management / Comment Editor | D24: =COUNTIF('API Catalog'!$B$4:$B$112,A24) -> 6 | E24: Hồ sơ, mật khẩu, avatar và tìm kiếm người dùng.
